xenon_core/__init__.py
xenon_core/xenon_core.cpython-311-x86_64-linux-gnu.so
xenon_core-0.4.0.dist-info/METADATA
xenon_core-0.4.0.dist-info/WHEEL
xenon_core-0.4.0.dist-info/RECORD
