Metadata-Version: 2.4
Name: xenon-core
Version: 0.4.0
Summary: High-performance computational biology library in Rust.
Requires-Python: >=3.8
